openqa_client/__init__.py
openqa_client/client.py
openqa_client/const.py
openqa_client/exceptions.py
openqa_client/py.typed
openqa_client-4.3.1.dist-info/licenses/COPYING
openqa_client-4.3.1.dist-info/METADATA
openqa_client-4.3.1.dist-info/WHEEL
openqa_client-4.3.1.dist-info/top_level.txt
openqa_client-4.3.1.dist-info/RECORD
