Metadata-Version: 2.4
Name: openqa_client
Version: 4.3.1
Summary: Python client library for openQA API
Home-page: https://github.com/os-autoinst/openQA-python-client
Author: Adam Williamson
Author-email: Adam Williamson <awilliam@redhat.com>
License:                     GNU GENERAL PUBLIC LICENSE
Project-URL: Homepage, https://github.com/os-autoinst/openQA-python-client
Project-URL: Bug Tracker, https://github.com/os-autoinst/openQA-python-client/issues
Keywords: openqa,opensuse,fedora,client
Classifier: Development Status :: 5 - Production/Stable
Classifier: Intended Audience :: Developers
Classifier: License :: OSI Approved :: GNU General Public License v2 or later (GPLv2+)
Classifier: Operating System :: OS Independent
Classifier: Programming Language :: Python :: 3
Classifier: Topic :: Utilities
Requires-Python: !=3.0.*, !=3.1.*, !=3.2.*, !=3.3.*, !=3.4.*, !=3.5.*, <4
License-File: COPYING
Requires-Dist: pyyaml
Requires-Dist: requests
Dynamic: author
Dynamic: home-page
Dynamic: license-file
Dynamic: requires-python
